pysourcesinfo/__init__.py
pysourcesinfo/__main__.py
pysourcesinfo-0.3.2.dist-info/AUTHORS.rst
pysourcesinfo-0.3.2.dist-info/LICENSE
pysourcesinfo-0.3.2.dist-info/METADATA
pysourcesinfo-0.3.2.dist-info/WHEEL
pysourcesinfo-0.3.2.dist-info/top_level.txt
pysourcesinfo-0.3.2.dist-info/RECORD
