Metadata-Version: 2.1
Name: pysourcesinfo
Version: 0.3.2
Summary: Python3 module and cli retrieving userful info from projects sources code, that can be later used in further steps in the context of a CI/CD pipeline for instance.
Home-page: https://github.com/weallfloatdownhere/pysourcesinfo
Author: redacted
Author-email: noreply@local.io
License: MIT license
Keywords: pysourcesinfo
Classifier: Development Status :: 2 - Pre-Alpha
Classifier: Intended Audience :: Developers
Classifier: License :: OSI Approved :: MIT License
Classifier: Natural Language :: English
Classifier: Programming Language :: Python :: 3
Classifier: Programming Language :: Python :: 3.6
Classifier: Programming Language :: Python :: 3.7
Classifier: Programming Language :: Python :: 3.8
Requires-Python: >=3.6
License-File: LICENSE
License-File: AUTHORS.rst
Requires-Dist: fire (==0.4.0)
Requires-Dist: omegaconf (==2.2.2)
Requires-Dist: ripgrepy (==1.1.0)
